apprisetransactions/__init__.py
apprisetransactions/backoff_hdlrs.py
apprisetransactions/cli.py
apprisetransactions/configuration.py
apprisetransactions/logging_config.ini
apprisetransactions/settings.py
apprisetransactions/utils.py
apprisetransactions/exceptions/__init__.py
apprisetransactions/exceptions/apprise_exceptions.py
apprisetransactions/exceptions/tx_exceptions.py
apprisetransactions/factories/__init__.py
apprisetransactions/factories/monero_factory.py
apprisetransactions/factories/transaction_factory.py
apprisetransactions/tests/__init__.py
apprisetransactions/tests/test_configuration.py
apprisetransactions/tests/test_monero_factory.py
apprisetransactions/tests/test_monero_transaction.py
apprisetransactions/tests/test_notify.py
apprisetransactions/tests/test_utils.py
apprisetransactions/transactions/__init__.py
apprisetransactions/transactions/monero_transaction.py
apprisetransactions/transactions/transaction.py
apprise_transactions-1.0.2.dist-info/LICENSE
apprise_transactions-1.0.2.dist-info/METADATA
apprise_transactions-1.0.2.dist-info/WHEEL
apprise_transactions-1.0.2.dist-info/entry_points.txt
apprise_transactions-1.0.2.dist-info/top_level.txt
apprise_transactions-1.0.2.dist-info/RECORD
