Metadata-Version: 2.1
Name: apprise-transactions
Version: 1.0.2
Summary: Push Notifications that work with just about every payment platform!
Home-page: https://github.com/apprises/apprise-transactions
Author: Apprises
Author-email: 
License: MIT
Keywords: Push Notifications Alerts Apprise Email AWS SNS Boxcar ClickSend Discord Dbus Emby Faast Flock Gitter Gnome Gotify Growl IFTTT Join Kavenegar KODI Kumulos MacOS Mailgun Matrix Mattermost MessageBird MSG91 Nexmo Nextcloud Notica Notifico Office365 Prowl PushBullet Pushjet Pushed Pushover PushSafer Rocket.Chat Ryver SendGrid SimplePush Sinch Slack Stride Syslog Techulus Push Telegram Twilio Twist Twitter XBMC Monero MSTeams Windows Webex CLI API
Platform: UNKNOWN
License-File: LICENSE
Requires-Dist: apprise (<=9.5.1)
Requires-Dist: monero (>=0.7.3)
Requires-Dist: argparse (>=1.4.0)
Requires-Dist: backoff (>=1.10.0)
Requires-Dist: dicttoxml (>=1.7.4)
